[{"start_epoch_second":1478952000,"rate_change":"All","id":"agc007","duration_second":6600,"title":"AtCoder Grand Contest 007"},{"start_epoch_second":1199113200,"rate_change":"×","id":"joi2008yo","duration_second":0,"title":"第７回日本情報オリンピック 予選（オンライン）"},{"start_epoch_second":1468065600,"rate_change":"All","id":"arc057","duration_second":5400,"title":"AtCoder Regular Contest 057"},{"start_epoch_second":1466251200,"rate_change":"All","id":"abc040","duration_second":7200,"title":"AtCoder Beginner Contest 040"},{"start_epoch_second":1441429200,"rate_change":"All","id":"tenka1-2015-final-open","duration_second":10800,"title":"天下一プログラマーコンテスト2015本戦（オープンコンテスト）"},{"start_epoch_second":1411214400,"rate_change":"All","id":"code-festival-2014-quala","duration_second":7200,"title":"CODE FESTIVAL 2014 予選A"},{"start_epoch_second":1492862400,"rate_change":"~ 2799","id":"arc072","duration_second":6000,"title":"AtCoder Regular Contest 072"},{"start_epoch_second":1431777600,"rate_change":"All","id":"arc039","duration_second":5400,"title":"AtCoder Regular Contest 039"},{"start_epoch_second":1339326000,"rate_change":"All","id":"hbpc2012","duration_second":5400,"title":"hasi's botsuneta programming contest"},{"start_epoch_second":1473595200,"rate_change":"~ 2799","id":"arc061","duration_second":6000,"title":"AtCoder Regular Contest 061"},{"start_epoch_second":1450584000,"rate_change":"All","id":"code-festival-2015-okinawa-open","duration_second":10800,"title":"CODE FESTIVAL 2015 OKINAWA OPEN"},{"start_epoch_second":1262271600,"rate_change":"×","id":"joisc2010","duration_second":0,"title":"2010年 日本情報オリンピック春合宿OJ"},{"start_epoch_second":1508673600,"rate_change":"All","id":"code-festival-2017-qualc","duration_second":7200,"title":"CODE FESTIVAL 2017 qual C"},{"start_epoch_second":1447472700,"rate_change":"All","id":"code-festival-2015-final-open","duration_second":10800,"title":"CODE FESTIVAL 2015 決勝（オープンコンテスト）"},{"start_epoch_second":1407585600,"rate_change":"All","id":"tenka1-2014-quala","duration_second":7200,"title":"天下一プログラマーコンテスト2014予選A"},{"start_epoch_second":1417921200,"rate_change":"All","id":"code-thanks-festival-2014-a-open","duration_second":10800,"title":"code thanks festival 2014 A日程（オープンコンテスト）"},{"start_epoch_second":1230735600,"rate_change":"×","id":"joisc2009","duration_second":0,"title":"2009年 日本情報オリンピック春合宿OJ"},{"start_epoch_second":1441429200,"rate_change":"All","id":"tenka1-2015-final","duration_second":10800,"title":"天下一プログラマーコンテスト2015本戦"},{"start_epoch_second":1340942400,"rate_change":"All","id":"kupc2012pr","duration_second":86400,"title":"京都大学プログラミングコンテスト2012 practice"},{"start_epoch_second":1500120000,"rate_change":"~ 1199","id":"abc067","duration_second":6000,"title":"AtCoder Beginner Contest 067"},{"start_epoch_second":1445774400,"rate_change":"All","id":"code-festival-2015-qualb","duration_second":7200,"title":"CODE FESTIVAL 2015 予選B"},{"start_epoch_second":1410660000,"rate_change":"All","id":"jag2014autumn","duration_second":18000,"title":"JAG Practice Contest for ACM-ICPC Asia Regional 2014"},{"start_epoch_second":1482573600,"rate_change":"×","id":"xmascon16","duration_second":14400,"title":"Xmas Contest 2016 夜の部"},{"start_epoch_second":1451574000,"rate_change":"×","id":"joi2016ho","duration_second":0,"title":"第１５回日本情報オリンピック 本選（オンライン）"},{"start_epoch_second":1506772800,"rate_change":"~ 2799","id":"tenka1-2017","duration_second":6000,"title":"Tenka1 Programmer Contest"},{"start_epoch_second":1447497600,"rate_change":"All","id":"code-festival-2015-exhibition-open","duration_second":3600,"title":"CODE FESTIVAL 2015 エキシビション（オープンコンテスト）"},{"start_epoch_second":1507982400,"rate_change":"~ 1199","id":"abc075","duration_second":6000,"title":"AtCoder Beginner Contest 075"},{"start_epoch_second":1325343600,"rate_change":"×","id":"joi2012yo","duration_second":0,"title":"第１１回日本情報オリンピック 予選（オンライン）"},{"start_epoch_second":1347872400,"rate_change":"All","id":"joiopen2012b","duration_second":18000,"title":"JOI Open Contest 2012 B"},{"start_epoch_second":1363998600,"rate_change":"×","id":"joisc2013-day4","duration_second":18000,"title":"2013年 日本情報オリンピック春合宿 4日目"},{"start_epoch_second":1482667200,"rate_change":"All","id":"agc008","duration_second":6600,"title":"AtCoder Grand Contest 008"},{"start_epoch_second":1450951200,"rate_change":"All","id":"xmascontest2015","duration_second":14400,"title":"Xmas Contest 2015 夜の部"},{"start_epoch_second":1403353800,"rate_change":"All","id":"abc011","duration_second":7200,"title":"AtCoder Beginner Contest 011"},{"start_epoch_second":1341115200,"rate_change":"All","id":"kupc2012","duration_second":18000,"title":"京都大学プログラミングコンテスト2012"},{"start_epoch_second":1489986000,"rate_change":"×","id":"rco-contest-2017-final-open","duration_second":14400,"title":"RCO presents 日本橋ハーフマラソン 本戦 (オープン)"},{"start_epoch_second":1483196400,"rate_change":"×","id":"joi2017ho","duration_second":0,"title":"第１６回日本情報オリンピック 本選（オンライン）"},{"start_epoch_second":1388502000,"rate_change":"×","id":"joisc2014","duration_second":0,"title":"2014年 日本情報オリンピック春合宿 オンラインジャッジ"},{"start_epoch_second":1483790400,"rate_change":"~ 1199","id":"abc051","duration_second":6000,"title":"AtCoder Beginner Contest 051"},{"start_epoch_second":1480156800,"rate_change":"×","id":"cf16-exhibition","duration_second":3600,"title":"CODE FESTIVAL 2016 Exhibition"},{"start_epoch_second":1417262400,"rate_change":"All","id":"arc030","duration_second":5400,"title":"AtCoder Regular Contest 030"},{"start_epoch_second":1334934000,"rate_change":"All","id":"ijpc2012pr","duration_second":2419200,"title":"IOIer Japan Programming Contest Practice"},{"start_epoch_second":1502020800,"rate_change":"~ 2799","id":"arc080","duration_second":6000,"title":"AtCoder Regular Contest 080"},{"start_epoch_second":1459598400,"rate_change":"All","id":"arc050","duration_second":5400,"title":"AtCoder Regular Contest 050"},{"start_epoch_second":1480156800,"rate_change":"×","id":"cf16-exhibition-open","duration_second":3600,"title":"CODE FESTIVAL 2016 Exhibition(Parallel)"},{"start_epoch_second":1334404800,"rate_change":"All","id":"arc001","duration_second":18000,"title":"AtCoder Regular Contest 001"},{"start_epoch_second":1397361600,"rate_change":"All","id":"JAG2014Spring","duration_second":18000,"title":"Japan Alumni Group Spring Contest 2014"},{"start_epoch_second":1230735600,"rate_change":"×","id":"joi2009yo","duration_second":0,"title":"第８回日本情報オリンピック 予選（オンライン）"},{"start_epoch_second":1440244800,"rate_change":"All","id":"tenka1-2015-qualb","duration_second":7200,"title":"天下一プログラマーコンテスト2015予選B"},{"start_epoch_second":1485604800,"rate_change":"~ 2799","id":"arc068","duration_second":6000,"title":"AtCoder Regular Contest 068"},{"start_epoch_second":1433592000,"rate_change":"All","id":"atc001","duration_second":5400,"title":"AtCoder Typical Contest 001"},{"start_epoch_second":1480131000,"rate_change":"All","id":"cf16-final-open","duration_second":10800,"title":"CODE FESTIVAL 2016 Final (Parallel)"},{"start_epoch_second":1495281600,"rate_change":"~ 1199","id":"abc062","duration_second":6000,"title":"AtCoder Beginner Contest 062"},{"start_epoch_second":1429963200,"rate_change":"All","id":"abc022","duration_second":7200,"title":"AtCoder Beginner Contest 022"},{"start_epoch_second":1501329600,"rate_change":"~ 2799","id":"arc079","duration_second":6000,"title":"AtCoder Regular Contest 079"},{"start_epoch_second":1476072000,"rate_change":"All","id":"code-festival-2016-qualb","duration_second":7200,"title":"CODE FESTIVAL 2016 qual B"},{"start_epoch_second":1167577200,"rate_change":"×","id":"joi2007yo","duration_second":0,"title":"第６回日本情報オリンピック 予選（オンライン）"},{"start_epoch_second":1399723200,"rate_change":"All","id":"abc008","duration_second":7200,"title":"AtCoder Beginner Contest 008"},{"start_epoch_second":1410570000,"rate_change":"All","id":"jag2014summer-day2","duration_second":18000,"title":"Japan Alumni Group Summer Camp 2014 Day 2"},{"start_epoch_second":1511006400,"rate_change":"~ 1199","id":"abc079","duration_second":6000,"title":"AtCoder Beginner Contest 079"},{"start_epoch_second":1456574400,"rate_change":"All","id":"mujin-pc-2016","duration_second":5400,"title":"MUJIN プログラミングチャレンジ Programming Challenge"},{"start_epoch_second":1377248400,"rate_change":"All","id":"tenka1-2013-qualb","duration_second":7200,"title":"天下一プログラマーコンテスト2013予選B"},{"start_epoch_second":1345201200,"rate_change":"All","id":"k2pc-hard","duration_second":7200,"title":"Kyuride Kagamiz Programming Contest (Hard)"},{"start_epoch_second":1475380800,"rate_change":"×","id":"kupc2016","duration_second":18000,"title":"Kyoto University Programming Contest 2016"},{"start_epoch_second":1360494000,"rate_change":"All","id":"arc012","duration_second":5400,"title":"AtCoder Regular Contest 012"},{"start_epoch_second":1487419200,"rate_change":"~ 1199","id":"abc055","duration_second":6000,"title":"AtCoder Beginner Contest 055"},{"start_epoch_second":1409400000,"rate_change":"All","id":"arc028","duration_second":5400,"title":"AtCoder Regular Contest 028"},{"start_epoch_second":1325343600,"rate_change":"×","id":"joi2012ho","duration_second":0,"title":"第１１回日本情報オリンピック 本選（オンライン）"},{"start_epoch_second":1480852800,"rate_change":"~ 1199","id":"abc048","duration_second":6000,"title":"AtCoder Beginner Contest 048"},{"start_epoch_second":1505563200,"rate_change":"~ 1199","id":"abc074","duration_second":6000,"title":"AtCoder Beginner Contest 074"},{"start_epoch_second":1500811200,"rate_change":"All","id":"agc018","duration_second":7800,"title":"AtCoder Grand Contest 018"},{"start_epoch_second":1437825600,"rate_change":"All","id":"arc042","duration_second":5400,"title":"AtCoder Regular Contest 042"},{"start_epoch_second":1342868400,"rate_change":"All","id":"arc006","duration_second":5400,"title":"AtCoder Regular Contest 006"},{"start_epoch_second":1503748800,"rate_change":"All","id":"agc019","duration_second":9000,"title":"AtCoder Grand Contest 019"},{"start_epoch_second":1511580600,"rate_change":"All","id":"cf17-final-open","duration_second":10800,"title":"CODE FESTIVAL 2017 Final (Parallel)"},{"start_epoch_second":1363912200,"rate_change":"×","id":"joisc2013-day3","duration_second":18000,"title":"2013年 日本情報オリンピック春合宿 3日目"},{"start_epoch_second":1439006400,"rate_change":"All","id":"tkppc","duration_second":14400,"title":"技術室奥プログラミングコンテスト"},{"start_epoch_second":1450933200,"rate_change":"All","id":"xmascontest2015noon","duration_second":14400,"title":"Xmas Contest 2015 昼の部"},{"start_epoch_second":1480852800,"rate_change":"~ 2799","id":"arc064","duration_second":6000,"title":"AtCoder Regular Contest 064"},{"start_epoch_second":1346230800,"rate_change":"All","id":"tenka1-2012-qualC","duration_second":7200,"title":"天下一プログラマーコンテスト2012 予選C"},{"start_epoch_second":1447546200,"rate_change":"All","id":"code-festival-2015-morning-hard","duration_second":5400,"title":"CODE FESTIVAL 2015 あさぷろ Hard"},{"start_epoch_second":1498910400,"rate_change":"~ 1199","id":"abc066","duration_second":6000,"title":"AtCoder Beginner Contest 066"},{"start_epoch_second":1463832000,"rate_change":"All","id":"arc054","duration_second":5400,"title":"AtCoder Regular Contest 054"},{"start_epoch_second":1491735600,"rate_change":"×","id":"s8pc-4","duration_second":12000,"title":"square869120Contest #4"},{"start_epoch_second":1472954400,"rate_change":"×","id":"jag2016autumn","duration_second":18000,"title":"JAG Practice Contest for ACM-ICPC Asia Regional 2016"},{"start_epoch_second":1424520000,"rate_change":"All","id":"arc034","duration_second":5400,"title":"AtCoder Regular Contest 034"},{"start_epoch_second":1502539200,"rate_change":"~ 1199","id":"abc070","duration_second":6000,"title":"AtCoder Beginner Contest 070"},{"start_epoch_second":1453546800,"rate_change":"All","id":"dwango2016-prelims","duration_second":7200,"title":"第2回 ドワンゴからの挑戦状 予選"},{"start_epoch_second":1496491200,"rate_change":"~ 2799","id":"arc075","duration_second":6000,"title":"AtCoder Regular Contest 075"},{"start_epoch_second":1480211700,"rate_change":"×","id":"cf16-tournament-round3-open","duration_second":2400,"title":"CODE FESTIVAL 2016 Tournament Round 3 (Parallel)"},{"start_epoch_second":1498305600,"rate_change":"~ 2799","id":"arc076","duration_second":6000,"title":"AtCoder Regular Contest 076"},{"start_epoch_second":1494072000,"rate_change":"All","id":"agc014","duration_second":7800,"title":"AtCoder Grand Contest 014"},{"start_epoch_second":1472385600,"rate_change":"~ 1199","id":"abc044","duration_second":6000,"title":"AtCoder Beginner Contest 044"},{"start_epoch_second":1455346800,"rate_change":"All","id":"dwango2016-finals","duration_second":7200,"title":"第2回 ドワンゴからの挑戦状 本選"},{"start_epoch_second":1478347200,"rate_change":"×","id":"ddcc2016-qual","duration_second":5400,"title":"DISCO presents ディスカバリーチャンネル コードコンテスト2016 予選"},{"start_epoch_second":1347854400,"rate_change":"All","id":"joiopen2012","duration_second":18000,"title":"JOI Open Contest 2012"},{"start_epoch_second":1386849600,"rate_change":"All","id":"abc003","duration_second":7200,"title":"AtCoder Beginner Contest 003"},{"start_epoch_second":1505563200,"rate_change":"~ 2799","id":"arc083","duration_second":6000,"title":"AtCoder Regular Contest 083"},{"start_epoch_second":1447546200,"rate_change":"All","id":"code-festival-2015-morning-easy","duration_second":5400,"title":"CODE FESTIVAL 2015 あさぷろ Easy"},{"start_epoch_second":1454760000,"rate_change":"All","id":"abc033","duration_second":7200,"title":"AtCoder Beginner Contest 033"},{"start_epoch_second":1425124800,"rate_change":"All","id":"abc019","duration_second":7200,"title":"AtCoder Beginner Contest 019"},{"start_epoch_second":1482555600,"rate_change":"×","id":"xmascon16noon","duration_second":14400,"title":"Xmas Contest 2016 昼の部"},{"start_epoch_second":1400328000,"rate_change":"All","id":"arc023","duration_second":5400,"title":"AtCoder Regular Contest 023"},{"start_epoch_second":1492862400,"rate_change":"~ 1199","id":"abc059","duration_second":6000,"title":"AtCoder Beginner Contest 059"},{"start_epoch_second":1469966400,"rate_change":"All","id":"agc002","duration_second":6600,"title":"AtCoder Grand Contest 002"},{"start_epoch_second":1377946800,"rate_change":"All","id":"tdpc","duration_second":18000,"title":"Typical DP Contest"},{"start_epoch_second":1412398800,"rate_change":"All","id":"code-formula-2014-final","duration_second":10800,"title":"Code Formula 2014 本選"},{"start_epoch_second":1391947200,"rate_change":"All","id":"arc017","duration_second":5400,"title":"AtCoder Regular Contest 017"},{"start_epoch_second":1490419200,"rate_change":"×","id":"yahoo-procon2017-final-open","duration_second":7200,"title":"「みんなのプロコン」本選 オープンコンテスト"},{"start_epoch_second":1480224300,"rate_change":"×","id":"cf16-relay-open","duration_second":5400,"title":"CODE FESTIVAL 2016 Relay (Parallel)"},{"start_epoch_second":1262271600,"rate_change":"×","id":"joi2010yo","duration_second":0,"title":"第９回日本情報オリンピック 予選（オンライン）"},{"start_epoch_second":1411819200,"rate_change":"All","id":"arc029","duration_second":5400,"title":"AtCoder Regular Contest 029"},{"start_epoch_second":1486209600,"rate_change":"All","id":"agc010","duration_second":6600,"title":"AtCoder Grand Contest 010"},{"start_epoch_second":1230735600,"rate_change":"×","id":"joi2009ho","duration_second":0,"title":"第８回日本情報オリンピック 本選（オンライン）"},{"start_epoch_second":1506056400,"rate_change":"×","id":"jag2017summer-day1","duration_second":10800,"title":"Japan Alumni Group Summer Camp 2017 Day 1"},{"start_epoch_second":1393675200,"rate_change":"All","id":"arc018","duration_second":5400,"title":"AtCoder Regular Contest 018"},{"start_epoch_second":1476532800,"rate_change":"~ 2799","id":"arc062","duration_second":6000,"title":"AtCoder Regular Contest 062"},{"start_epoch_second":1452945600,"rate_change":"All","id":"arc047","duration_second":5400,"title":"AtCoder Regular Contest 047"},{"start_epoch_second":1507464000,"rate_change":"All","id":"code-festival-2017-qualb","duration_second":7200,"title":"CODE FESTIVAL 2017 qual B"},{"start_epoch_second":1438430400,"rate_change":"All","id":"tenka1-2015-quala","duration_second":7200,"title":"天下一プログラマーコンテスト2015予選A"},{"start_epoch_second":1512183600,"rate_change":"×","id":"code-thanks-festival-2017","duration_second":10800,"title":"CODE THANKS FESTIVAL 2017"},{"start_epoch_second":1509796800,"rate_change":"~ 2799","id":"arc084","duration_second":6000,"title":"AtCoder Regular Contest 084"},{"start_epoch_second":1444478400,"rate_change":"All","id":"arc045","duration_second":5400,"title":"AtCoder Regular Contest 045"},{"start_epoch_second":1489320000,"rate_change":"All","id":"agc011","duration_second":6600,"title":"AtCoder Grand Contest 011"},{"start_epoch_second":1442106000,"rate_change":"All","id":"jag2015summer-day3","duration_second":18000,"title":"Japan Alumni Group Summer Camp 2015 Day 3"},{"start_epoch_second":1438488000,"rate_change":"All","id":"yuha-c88","duration_second":18000,"title":"YUHA presents C88 謎解き×競技プログラミング 『ある勇者の物語』"},{"start_epoch_second":1405166400,"rate_change":"All","id":"abc012","duration_second":7200,"title":"AtCoder Beginner Contest 012"},{"start_epoch_second":1293807600,"rate_change":"×","id":"joi2011yo","duration_second":0,"title":"第１０回日本情報オリンピック 予選（オンライン）"},{"start_epoch_second":1409979600,"rate_change":"All","id":"tenka1-2014-final","duration_second":10800,"title":"天下一プログラマーコンテスト2014 本戦"},{"start_epoch_second":1408532400,"rate_change":"All","id":"code-formula-2014-quala","duration_second":7200,"title":"Code Formula 2014 予選A"},{"start_epoch_second":1484481600,"rate_change":"~ 1199","id":"abc052","duration_second":6000,"title":"AtCoder Beginner Contest 052"},{"start_epoch_second":1428148800,"rate_change":"All","id":"arc036","duration_second":5400,"title":"AtCoder Regular Contest 036"},{"start_epoch_second":1477742400,"rate_change":"All","id":"agc006","duration_second":7800,"title":"AtCoder Grand Contest 006"},{"start_epoch_second":1451574000,"rate_change":"×","id":"joi2016yo","duration_second":0,"title":"第１５回日本情報オリンピック 予選（オンライン）"},{"start_epoch_second":1402747200,"rate_change":"All","id":"arc025","duration_second":5400,"title":"AtCoder Regular Contest 025"},{"start_epoch_second":1408795200,"rate_change":"All","id":"tenka1-2014-qualb","duration_second":7200,"title":"天下一プログラマーコンテスト2014予選B"},{"start_epoch_second":1511661900,"rate_change":"×","id":"cf17-tournament-round2-open","duration_second":1800,"title":"CODE FESTIVAL 2017 Elimination Tournament Round 2 (Parallel)"},{"start_epoch_second":1418526000,"rate_change":"All","id":"code-thanks-festival-2014-b-open","duration_second":10800,"title":"code thanks festival 2014 B日程（オープンコンテスト）"},{"start_epoch_second":1420342200,"rate_change":"All","id":"NYC2015","duration_second":18000,"title":"New Year Contest 2015"},{"start_epoch_second":1381579200,"rate_change":"All","id":"abc001","duration_second":7200,"title":"AtCoder Beginner Contest 001"},{"start_epoch_second":1430798400,"rate_change":"All","id":"gwcontest2015","duration_second":14400,"title":"Golden Week Contest 2015"},{"start_epoch_second":1458993600,"rate_change":"All","id":"abc035","duration_second":7200,"title":"AtCoder Beginner Contest 035"},{"start_epoch_second":1445688000,"rate_change":"All","id":"abc030","duration_second":7200,"title":"AtCoder Beginner Contest 030"},{"start_epoch_second":1427350800,"rate_change":"All","id":"indeednow-finala-open","duration_second":7200,"title":"Indeedなう（オープンコンテスト）"},{"start_epoch_second":1467460800,"rate_change":"All","id":"abc041","duration_second":7200,"title":"AtCoder Beginner Contest 041"},{"start_epoch_second":1501329600,"rate_change":"~ 1199","id":"abc068","duration_second":6000,"title":"AtCoder Beginner Contest 068"},{"start_epoch_second":1481371200,"rate_change":"~ 2799","id":"arc065","duration_second":6000,"title":"AtCoder Regular Contest 065"},{"start_epoch_second":1345251600,"rate_change":"All","id":"tenka1-2012-qualB","duration_second":7200,"title":"天下一プログラマーコンテスト2012 予選B"},{"start_epoch_second":1410609600,"rate_change":"All","id":"abc014","duration_second":7200,"title":"AtCoder Beginner Contest 014"},{"start_epoch_second":1375527600,"rate_change":"All","id":"tenka1-2013-quala","duration_second":7200,"title":"天下一プログラマーコンテスト2013予選A"},{"start_epoch_second":1493467200,"rate_change":"~ 2799","id":"arc073","duration_second":6000,"title":"AtCoder Regular Contest 073"},{"start_epoch_second":1496491200,"rate_change":"~ 1199","id":"abc063","duration_second":6000,"title":"AtCoder Beginner Contest 063"},{"start_epoch_second":1435406400,"rate_change":"All","id":"abc025","duration_second":7200,"title":"AtCoder Beginner Contest 025"},{"start_epoch_second":1483196400,"rate_change":"×","id":"joisc2017","duration_second":0,"title":"JOI春合宿2017 オンラインジャッジ"},{"start_epoch_second":1431172800,"rate_change":"All","id":"abc023","duration_second":7200,"title":"AtCoder Beginner Contest 023"},{"start_epoch_second":1460808000,"rate_change":"All","id":"arc051","duration_second":5400,"title":"AtCoder Regular Contest 051"},{"start_epoch_second":1448253000,"rate_change":"All","id":"ijpc2015-2","duration_second":18000,"title":"IOIer Japan Programming Contest 2015"},{"start_epoch_second":1470542400,"rate_change":"×","id":"tkppc2","duration_second":14400,"title":"技術室奥プログラミングコンテスト#2"},{"start_epoch_second":1490529600,"rate_change":"~ 1199","id":"abc057","duration_second":6000,"title":"AtCoder Beginner Contest 057"},{"start_epoch_second":1342929600,"rate_change":"All","id":"ijpc2012-3","duration_second":18000,"title":"IOIer Japan Programming Contest #3"},{"start_epoch_second":1347102000,"rate_change":"All","id":"arc007","duration_second":5400,"title":"AtCoder Regular Contest 007"},{"start_epoch_second":1476532800,"rate_change":"~ 1199","id":"abc046","duration_second":6000,"title":"AtCoder Beginner Contest 046"},{"start_epoch_second":1419141600,"rate_change":"All","id":"code-festival-2014-china-open","duration_second":10800,"title":"code festival 2014 上海（オープンコンテスト）"},{"start_epoch_second":1447564500,"rate_change":"All","id":"code-festival-2015-relay","duration_second":5400,"title":"CODE FESTIVAL2015チーム対抗早解きリレー"},{"start_epoch_second":1456642872,"rate_change":"All","id":"oidashi","duration_second":10680,"title":"TPC追いコン"},{"start_epoch_second":1432382400,"rate_change":"All","id":"abc024","duration_second":7200,"title":"AtCoder Beginner Contest 024"},{"start_epoch_second":1480206000,"rate_change":"×","id":"cf16-tournament-round1-open","duration_second":1800,"title":"CODE FESTIVAL 2016 Elimination Tournament Round 1 (Parallel)"},{"start_epoch_second":1457784000,"rate_change":"All","id":"abc034","duration_second":7200,"title":"AtCoder Beginner Contest 034"},{"start_epoch_second":1423051200,"rate_change":"All","id":"abc018","duration_second":7200,"title":"AtCoder Beginner Contest 018"},{"start_epoch_second":1416024000,"rate_change":"All","id":"k4pc","duration_second":14400,"title":"KyurideKagamizProgrammingContest(Remixed by ryunosuKe & Kensuke)"},{"start_epoch_second":1397908800,"rate_change":"All","id":"abc007","duration_second":7200,"title":"AtCoder Beginner Contest 007"},{"start_epoch_second":1372568400,"rate_change":"All","id":"geocon2013","duration_second":10800,"title":"幾何コンテスト2013"},{"start_epoch_second":1399118400,"rate_change":"All","id":"arc022","duration_second":5400,"title":"AtCoder Regular Contest 022"},{"start_epoch_second":1497096000,"rate_change":"~ 1199","id":"abc064","duration_second":6000,"title":"AtCoder Beginner Contest 064"},{"start_epoch_second":1473595200,"rate_change":"~ 1199","id":"abc045","duration_second":6000,"title":"AtCoder Beginner Contest 045"},{"start_epoch_second":1478433600,"rate_change":"~ 1199","id":"abc047","duration_second":6000,"title":"AtCoder Beginner Contest 047"},{"start_epoch_second":1491652800,"rate_change":"~ 1199","id":"abc058","duration_second":6000,"title":"AtCoder Beginner Contest 058"},{"start_epoch_second":1490419200,"rate_change":"×","id":"yahoo-procon2017-final","duration_second":7200,"title":"「みんなのプロコン」本選"},{"start_epoch_second":1447497600,"rate_change":"All","id":"code-festival-2015-exhibition","duration_second":3600,"title":"CODE FESTIVAL 2015 エキシビション"},{"start_epoch_second":1480728600,"rate_change":"×","id":"ddcc2016-final","duration_second":7200,"title":"DISCO presents ディスカバリーチャンネル コードコンテスト2016 本戦"},{"start_epoch_second":1373083200,"rate_change":"All","id":"kupc2013","duration_second":18000,"title":"京都大学プログラミングコンテスト2013"},{"start_epoch_second":1460203200,"rate_change":"All","id":"abc036","duration_second":7200,"title":"AtCoder Beginner Contest 036"},{"start_epoch_second":1350792000,"rate_change":"All","id":"autumn_fest","duration_second":18000,"title":"Autumn Fest 2012"},{"start_epoch_second":1423648800,"rate_change":"All","id":"donuts-2015","duration_second":5400,"title":"Donutsプロコンチャレンジ2015"},{"start_epoch_second":1442664000,"rate_change":"All","id":"abc029","duration_second":7200,"title":"AtCoder Beginner Contest 029"},{"start_epoch_second":1464955200,"rate_change":"All","id":"arc055","duration_second":5400,"title":"AtCoder Regular Contest 055"},{"start_epoch_second":1293807600,"rate_change":"×","id":"joi2011ho","duration_second":0,"title":"第１０回日本情報オリンピック 本選（オンライン）"},{"start_epoch_second":1502020800,"rate_change":"~ 1199","id":"abc069","duration_second":6000,"title":"AtCoder Beginner Contest 069"},{"start_epoch_second":1448157600,"rate_change":"All","id":"jag2015autumn","duration_second":18000,"title":"JAG Practice Contest for ACM-ICPC Asia Regional 2015"},{"start_epoch_second":1442059200,"rate_change":"All","id":"arc044","duration_second":5400,"title":"AtCoder Regular Contest 044"},{"start_epoch_second":1471089600,"rate_change":"~ 2799","id":"arc059","duration_second":6000,"title":"AtCoder Regular Contest 059"},{"start_epoch_second":1379725200,"rate_change":"All","id":"jag2013summer-warmingup","duration_second":10800,"title":"Japan Alumni Group Summer Camp 2013 Warming Up"},{"start_epoch_second":1408190400,"rate_change":"All","id":"abc013","duration_second":7200,"title":"AtCoder Beginner Contest 013"},{"start_epoch_second":1485604800,"rate_change":"~ 1199","id":"abc053","duration_second":6000,"title":"AtCoder Beginner Contest 053"},{"start_epoch_second":1442022000,"rate_change":"All","id":"jag2015summer-day2","duration_second":18000,"title":"Japan Alumni Group Summer Camp 2015 Day 2"},{"start_epoch_second":1471780800,"rate_change":"All","id":"agc003","duration_second":6600,"title":"AtCoder Grand Contest 003"},{"start_epoch_second":1409979600,"rate_change":"All","id":"tenka1-2014-final-open","duration_second":10800,"title":"天下一プログラマーコンテスト2014本戦（オープンコンテスト）"},{"start_epoch_second":1469880000,"rate_change":"×","id":"tenka1-2016-quala","duration_second":7200,"title":"天下一プログラマーコンテスト2016予選A"},{"start_epoch_second":1485666000,"rate_change":"×","id":"njpc2017","duration_second":10800,"title":"NJPC2017"},{"start_epoch_second":1338116400,"rate_change":"All","id":"arc003","duration_second":5400,"title":"AtCoder Regular Contest 003"},{"start_epoch_second":1262271600,"rate_change":"×","id":"joi2010ho","duration_second":0,"title":"第９回日本情報オリンピック 本選（オンライン）"},{"start_epoch_second":1480209000,"rate_change":"×","id":"cf16-tournament-round2-open","duration_second":1800,"title":"CODE FESTIVAL 2016 Elimination Tournament Round 2 (Parallel)"},{"start_epoch_second":1499601600,"rate_change":"All","id":"agc017","duration_second":7200,"title":"AtCoder Grand Contest 017"},{"start_epoch_second":1453633200,"rate_change":"All","id":"s8pc-1","duration_second":9000,"title":"square869120Contest #1"},{"start_epoch_second":1167577200,"rate_change":"×","id":"joisc2007","duration_second":0,"title":"2007年 日本情報オリンピック春合宿OJ"},{"start_epoch_second":1511580600,"rate_change":"All","id":"cf17-final","duration_second":10800,"title":"CODE FESTIVAL 2017 Final"},{"start_epoch_second":1386244800,"rate_change":"All","id":"tricky","duration_second":7200,"title":"トリッキー問題コンテスト"},{"start_epoch_second":1443268800,"rate_change":"All","id":"code-festival-2015-quala","duration_second":7200,"title":"CODE FESTIVAL 2015 予選A"},{"start_epoch_second":1510401600,"rate_change":"~ 1199","id":"abc078","duration_second":6000,"title":"AtCoder Beginner Contest 078"},{"start_epoch_second":1358596800,"rate_change":"All","id":"arc011","duration_second":5400,"title":"AtCoder Regular Contest 011"},{"start_epoch_second":1489838400,"rate_change":"~ 1199","id":"abc056","duration_second":6000,"title":"AtCoder Beginner Contest 056"},{"start_epoch_second":1345201200,"rate_change":"All","id":"k2pc-easy","duration_second":7200,"title":"Kyuride Kagamiz Programming Contest (Easy)"},{"start_epoch_second":1436011200,"rate_change":"All","id":"arc041","duration_second":5400,"title":"AtCoder Regular Contest 041"},{"start_epoch_second":1488625200,"rate_change":"×","id":"rco-contest-2017-qual","duration_second":10800,"title":"RCO presents 日本橋ハーフマラソン 予選"},{"start_epoch_second":1484380800,"rate_change":"×","id":"dwacon2017-honsen","duration_second":3600,"title":"第3回 ドワンゴからの挑戦状 本選(オープンコンテスト)"},{"start_epoch_second":1458446400,"rate_change":"All","id":"chokudai001","duration_second":28800,"title":"Chokudai Contest 001"},{"start_epoch_second":1504958400,"rate_change":"~ 1199","id":"abc073","duration_second":6000,"title":"AtCoder Beginner Contest 073"},{"start_epoch_second":1422705600,"rate_change":"All","id":"arc033","duration_second":5400,"title":"AtCoder Regular Contest 033"},{"start_epoch_second":1420038000,"rate_change":"×","id":"joi2015ho","duration_second":0,"title":"第１４回日本情報オリンピック 本選（オンライン）"},{"start_epoch_second":1477224000,"rate_change":"All","id":"code-festival-2016-qualc","duration_second":7200,"title":"CODE FESTIVAL 2016 qual C"},{"start_epoch_second":1363825800,"rate_change":"×","id":"joisc2013-day2","duration_second":18000,"title":"2013年 日本情報オリンピック春合宿 2日目"},{"start_epoch_second":1506772800,"rate_change":"~ 1199","id":"tenka1-2017-beginner","duration_second":6000,"title":"Tenka1 Programmer Beginner Contest"},{"start_epoch_second":1371380400,"rate_change":"All","id":"arc014","duration_second":5400,"title":"AtCoder Regular Contest 014"},{"start_epoch_second":1427601600,"rate_change":"All","id":"utpc2014","duration_second":18000,"title":"東京大学プログラミングコンテスト2014"},{"start_epoch_second":1448107200,"rate_change":"All","id":"abc031","duration_second":7200,"title":"AtCoder Beginner Contest 031"},{"start_epoch_second":1454155200,"rate_change":"All","id":"discovery2016-qual","duration_second":5400,"title":"DISCO presents ディスカバリーチャンネル プログラミングコンテスト2016 予選"},{"start_epoch_second":1348311600,"rate_change":"All","id":"arc008","duration_second":5400,"title":"AtCoder Regular Contest 008"},{"start_epoch_second":1504353600,"rate_change":"~ 2799","id":"arc082","duration_second":6000,"title":"AtCoder Regular Contest 082"},{"start_epoch_second":1457179200,"rate_change":"All","id":"arc048","duration_second":5400,"title":"AtCoder Regular Contest 048"},{"start_epoch_second":1480302000,"rate_change":"All","id":"cf16-exhibition-final","duration_second":10800,"title":"CODE FESTIVAL 2016 Grand Final"},{"start_epoch_second":1338613200,"rate_change":"All","id":"wupc2012-closed","duration_second":7200,"title":"WUPC2012 (Closed)"},{"start_epoch_second":1388502000,"rate_change":"×","id":"joi2014yo","duration_second":0,"title":"第１３回日本情報オリンピック 予選（オンライン）"},{"start_epoch_second":1503230400,"rate_change":"~ 1199","id":"abc071","duration_second":6000,"title":"AtCoder Beginner Contest 071"},{"start_epoch_second":1421496000,"rate_change":"All","id":"abc017","duration_second":7200,"title":"AtCoder Beginner Contest 017"},{"start_epoch_second":1378558800,"rate_change":"All","id":"language-test-ver1","duration_second":3600,"title":"Language Test ver1"},{"start_epoch_second":1498910400,"rate_change":"~ 2799","id":"arc077","duration_second":6000,"title":"AtCoder Regular Contest 077"},{"start_epoch_second":1461409200,"rate_change":"All","id":"s8pc-2","duration_second":10800,"title":"square869120Contest #2"},{"start_epoch_second":1442192400,"rate_change":"All","id":"jag2015summer-day4","duration_second":18000,"title":"Japan Alumni Group Summer Camp 2015 Day 4"},{"start_epoch_second":1462017600,"rate_change":"All","id":"arc052","duration_second":5400,"title":"AtCoder Regular Contest 052"},{"start_epoch_second":1394884800,"rate_change":"All","id":"arc019","duration_second":5400,"title":"AtCoder Regular Contest 019"},{"start_epoch_second":1469275200,"rate_change":"~ 1199","id":"abc042","duration_second":6000,"title":"AtCoder Beginner Contest 042"},{"start_epoch_second":1420038000,"rate_change":"×","id":"joi2015yo","duration_second":0,"title":"第１４回日本情報オリンピック 予選（オンライン）"},{"start_epoch_second":1449284400,"rate_change":"All","id":"code-thanks-festival-2015-open","duration_second":10800,"title":"CODE THANKS FESTIVAL 2015 オープンコンテスト"},{"start_epoch_second":1410742800,"rate_change":"All","id":"jag2014summer-day4","duration_second":18000,"title":"Japan Alumni Group Summer Camp 2014 Day 4"},{"start_epoch_second":1455931800,"rate_change":"All","id":"discovery2016-final","duration_second":7200,"title":"DISCO presents ディスカバリーチャンネル プログラミングコンテスト2016 本選"},{"start_epoch_second":1382875200,"rate_change":"All","id":"abc002","duration_second":7200,"title":"AtCoder Beginner Contest 002"},{"start_epoch_second":1495281600,"rate_change":"~ 2799","id":"arc074","duration_second":6000,"title":"AtCoder Regular Contest 074"},{"start_epoch_second":1491048000,"rate_change":"All","id":"agc012","duration_second":6600,"title":"AtCoder Grand Contest 012"},{"start_epoch_second":1339848000,"rate_change":"All","id":"arc004","duration_second":5400,"title":"AtCoder Regular Contest 004"},{"start_epoch_second":1471089600,"rate_change":"~ 1199","id":"abc043","duration_second":6000,"title":"AtCoder Beginner Contest 043"},{"start_epoch_second":1415443200,"rate_change":"All","id":"code-festival-2014-exhibition-open","duration_second":3600,"title":"CODE FESTIVAL 2014 エキシビション（オープン）"},{"start_epoch_second":1480302000,"rate_change":"×","id":"cf16-exhibition-final-open","duration_second":10800,"title":"CODE FESTIVAL 2016 Grand Final(Parallel)"},{"start_epoch_second":1353754800,"rate_change":"All","id":"digitalarts2012","duration_second":3600,"title":"DigitalArts プログラミングコンテスト2012"},{"start_epoch_second":1506168000,"rate_change":"All","id":"code-festival-2017-quala","duration_second":7200,"title":"CODE FESTIVAL 2017 qual A"},{"start_epoch_second":1486814400,"rate_change":"~ 1199","id":"abc054","duration_second":6000,"title":"AtCoder Beginner Contest 054"},{"start_epoch_second":1480131000,"rate_change":"All","id":"cf16-final","duration_second":10800,"title":"CODE FESTIVAL 2016 Final"},{"start_epoch_second":1423897200,"rate_change":"All","id":"dwango2015-finals","duration_second":7200,"title":"dwangoプログラミングコンテスト"},{"start_epoch_second":1498305600,"rate_change":"~ 1199","id":"abc065","duration_second":6000,"title":"AtCoder Beginner Contest 065"},{"start_epoch_second":1481972400,"rate_change":"×","id":"dwacon2017-prelims","duration_second":7200,"title":"第3回 ドワンゴからの挑戦状 予選"},{"start_epoch_second":1482062400,"rate_change":"~ 2799","id":"arc066","duration_second":6000,"title":"AtCoder Regular Contest 066"},{"start_epoch_second":1511659200,"rate_change":"×","id":"cf17-tournament-round1-open","duration_second":1800,"title":"CODE FESTIVAL 2017 Elimination Tournament Round 1 (Parallel)"},{"start_epoch_second":1440849600,"rate_change":"All","id":"abc028","duration_second":7200,"title":"AtCoder Beginner Contest 028"},{"start_epoch_second":1495886400,"rate_change":"All","id":"agc015","duration_second":6600,"title":"AtCoder Grand Contest 015"},{"start_epoch_second":1429358400,"rate_change":"All","id":"arc037","duration_second":5400,"title":"AtCoder Regular Contest 037"},{"start_epoch_second":1384048800,"rate_change":"All","id":"jag2013autumn","duration_second":18000,"title":"JAG Practice Contest for ACM-ICPC Asia Regional 2013"},{"start_epoch_second":1427782800,"rate_change":"All","id":"indeednow-finalb-open","duration_second":7200,"title":"Indeedなう（オープンコンテストB）"},{"start_epoch_second":1396699200,"rate_change":"All","id":"abc006","duration_second":7200,"title":"AtCoder Beginner Contest 006"},{"start_epoch_second":1379898000,"rate_change":"All","id":"jag2013summer-day4","duration_second":18000,"title":"Japan Alumni Group Summer Camp 2013 Day 4"},{"start_epoch_second":1426680000,"rate_change":"All","id":"indeednow-qualb","duration_second":7200,"title":"Indeedなう（予選B）"},{"start_epoch_second":1393732800,"rate_change":"All","id":"utpc2013","duration_second":18000,"title":"東京大学プログラミングコンテスト2013"},{"start_epoch_second":1343995200,"rate_change":"All","id":"tenka1-2012-qualA","duration_second":7200,"title":"天下一プログラマーコンテスト2012 予選A"},{"start_epoch_second":1501243800,"rate_change":"×","id":"chokudai_S001","duration_second":3600,"title":"Chokudai SpeedRun 001"},{"start_epoch_second":1451574000,"rate_change":"×","id":"joisc2016","duration_second":0,"title":"JOI春合宿2016 オンラインジャッジ"},{"start_epoch_second":1478433600,"rate_change":"~ 2799","id":"arc063","duration_second":6000,"title":"AtCoder Regular Contest 063"},{"start_epoch_second":1363739400,"rate_change":"×","id":"joisc2013-day1","duration_second":18000,"title":"2013年 日本情報オリンピック春合宿 1日目"},{"start_epoch_second":1397304000,"rate_change":"All","id":"arc021","duration_second":5400,"title":"AtCoder Regular Contest 021"},{"start_epoch_second":1491652800,"rate_change":"~ 2799","id":"arc071","duration_second":6000,"title":"AtCoder Regular Contest 071"},{"start_epoch_second":1136041200,"rate_change":"×","id":"joi2006ho","duration_second":0,"title":"第５回日本情報オリンピック 本選（オンライン）"},{"start_epoch_second":1472990400,"rate_change":"All","id":"agc004","duration_second":6600,"title":"AtCoder Grand Contest 004"},{"start_epoch_second":1420286400,"rate_change":"All","id":"arc032","duration_second":5400,"title":"AtCoder Regular Contest 032"},{"start_epoch_second":1422097200,"rate_change":"All","id":"dwango2015-prelims","duration_second":7200,"title":"dwangoプログラミングコンテスト"},{"start_epoch_second":1506830400,"rate_change":"×","id":"kupc2017","duration_second":18000,"title":"Kyoto University Programming Contest 2017"},{"start_epoch_second":1473483600,"rate_change":"×","id":"tenka1-2016-final","duration_second":9000,"title":"天下一プログラマーコンテスト2016本戦"},{"start_epoch_second":1509796800,"rate_change":"~ 1199","id":"abc077","duration_second":6000,"title":"AtCoder Beginner Contest 077"},{"start_epoch_second":1509672600,"rate_change":"×","id":"ddcc2017-final","duration_second":7200,"title":"DISCO presents ディスカバリーチャンネル コードコンテスト2017 本戦"},{"start_epoch_second":1510401600,"rate_change":"~ 2799","id":"arc085","duration_second":6000,"title":"AtCoder Regular Contest 085"},{"start_epoch_second":1404532800,"rate_change":"All","id":"kupc2014","duration_second":18000,"title":"京都大学プログラミングコンテスト2014"},{"start_epoch_second":1455350400,"rate_change":"All","id":"dwango2016-honsen","duration_second":3600,"title":"第2回 ドワンゴからの挑戦状 本選(オープンコンテスト)"},{"start_epoch_second":1465646400,"rate_change":"All","id":"abc039","duration_second":7200,"title":"AtCoder Beginner Contest 039"},{"start_epoch_second":1395489600,"rate_change":"All","id":"abc005","duration_second":7200,"title":"AtCoder Beginner Contest 005"},{"start_epoch_second":1325343600,"rate_change":"×","id":"joisc2012","duration_second":0,"title":"2012年 日本情報オリンピック春合宿OJ"},{"start_epoch_second":1379134800,"rate_change":"All","id":"tenka1-2013-final","duration_second":10800,"title":"天下一プログラマーコンテスト2013 決勝"},{"start_epoch_second":1439035200,"rate_change":"All","id":"abc027","duration_second":7200,"title":"AtCoder Beginner Contest 027"},{"start_epoch_second":1384574400,"rate_change":"All","id":"maximum-cup-2013","duration_second":18000,"title":"Maximum-Cup 2013"},{"start_epoch_second":1469275200,"rate_change":"~ 2799","id":"arc058","duration_second":6000,"title":"AtCoder Regular Contest 058"},{"start_epoch_second":1395975600,"rate_change":"All","id":"qupc2014","duration_second":18000,"title":"九州大学プログラミングコンテスト2014"},{"start_epoch_second":1403956800,"rate_change":"All","id":"arc026","duration_second":5400,"title":"AtCoder Regular Contest 026"},{"start_epoch_second":1379811600,"rate_change":"All","id":"jag2013summer-day3","duration_second":18000,"title":"Japan Alumni Group Summer Camp 2013 Day 3"},{"start_epoch_second":1483196400,"rate_change":"×","id":"joi2017yo","duration_second":0,"title":"第１６回日本情報オリンピック 予選（オンライン）"},{"start_epoch_second":1466856000,"rate_change":"All","id":"arc056","duration_second":5400,"title":"AtCoder Regular Contest 056"},{"start_epoch_second":1351994400,"rate_change":"All","id":"jag2012autumn","duration_second":18000,"title":"JAG Practice Contest for ACM-ICPC Asia Regional 2012"},{"start_epoch_second":1426939200,"rate_change":"All","id":"abc020","duration_second":7200,"title":"AtCoder Beginner Contest 020"},{"start_epoch_second":1468670400,"rate_change":"All","id":"agc001","duration_second":6600,"title":"AtCoder Grand Contest 001"},{"start_epoch_second":1507377600,"rate_change":"×","id":"ddcc2017-qual","duration_second":5400,"title":"DISCO presents ディスカバリーチャンネル コードコンテスト2017 予選"},{"start_epoch_second":1478170800,"rate_change":"×","id":"chokudai002","duration_second":10800,"title":"Chokudai Contest 002"},{"start_epoch_second":1512183600,"rate_change":"×","id":"code-thanks-festival-2017-open","duration_second":10800,"title":"CODE THANKS FESTIVAL 2017(Parallel)"},{"start_epoch_second":1510671600,"rate_change":"×","id":"hokudai-hitachi2017-1","duration_second":1209540,"title":"Hokkaido Univ.& Hitachi 1st New-concept Computing Contest 2017"},{"start_epoch_second":1356667200,"rate_change":"All","id":"yuha-c83","duration_second":18000,"title":"YUHA presents C83 新刊 『競技プログラミング The Boss Rush!!!』"},{"start_epoch_second":1472385600,"rate_change":"~ 2799","id":"arc060","duration_second":6000,"title":"AtCoder Regular Contest 060"},{"start_epoch_second":1487419200,"rate_change":"~ 2799","id":"arc069","duration_second":6000,"title":"AtCoder Regular Contest 069"},{"start_epoch_second":1355659200,"rate_change":"All","id":"arc010","duration_second":5400,"title":"AtCoder Regular Contest 010"},{"start_epoch_second":1380974400,"rate_change":"All","id":"arc015","duration_second":5400,"title":"AtCoder Regular Contest 015"},{"start_epoch_second":1472299200,"rate_change":"×","id":"tenka1-2016-qualb","duration_second":7200,"title":"天下一プログラマーコンテスト2016予選B"},{"start_epoch_second":1504353600,"rate_change":"~ 1199","id":"abc072","duration_second":6000,"title":"AtCoder Beginner Contest 072"},{"start_epoch_second":1417867500,"rate_change":"All","id":"abc016","duration_second":7200,"title":"AtCoder Beginner Contest 016"},{"start_epoch_second":1434196800,"rate_change":"All","id":"arc040","duration_second":5400,"title":"AtCoder Regular Contest 040"},{"start_epoch_second":1484481600,"rate_change":"~ 2799","id":"arc067","duration_second":6000,"title":"AtCoder Regular Contest 067"},{"start_epoch_second":1435986000,"rate_change":"All","id":"snuke21","duration_second":18000,"title":"すぬけのお誕生日コンテスト"},{"start_epoch_second":1415514600,"rate_change":"All","id":"code-festival-2014-relay","duration_second":5400,"title":"CODE FESTIVAL 2014チーム対抗早解きリレー"},{"start_epoch_second":1494676800,"rate_change":"~ 1199","id":"abc061","duration_second":6000,"title":"AtCoder Beginner Contest 061"},{"start_epoch_second":1420038000,"rate_change":"×","id":"joisc2015","duration_second":0,"title":"JOI春合宿2015 オンラインジャッジ"},{"start_epoch_second":1482062400,"rate_change":"~ 1199","id":"abc050","duration_second":6000,"title":"AtCoder Beginner Contest 050"},{"start_epoch_second":1402142400,"rate_change":"All","id":"abc010","duration_second":7200,"title":"AtCoder Beginner Contest 010"},{"start_epoch_second":1350734400,"rate_change":"All","id":"arc009","duration_second":5400,"title":"AtCoder Regular Contest 009"},{"start_epoch_second":1335960000,"rate_change":"All","id":"arc002","duration_second":5400,"title":"AtCoder Regular Contest 002"},{"start_epoch_second":1428753600,"rate_change":"All","id":"abc021","duration_second":7200,"title":"AtCoder Beginner Contest 021"},{"start_epoch_second":1337486400,"rate_change":"All","id":"ijpc2012-1","duration_second":18000,"title":"IOIer Japan Programming Contest #1"},{"start_epoch_second":1511677800,"rate_change":"×","id":"cf17-relay-open","duration_second":5400,"title":"Code Festival Team Relay (Parallel)"},{"start_epoch_second":1414324800,"rate_change":"All","id":"code-festival-2014-qualb","duration_second":7200,"title":"CODE FESTIVAL 2014 予選B"},{"start_epoch_second":1338613200,"rate_change":"All","id":"wupc2012","duration_second":7200,"title":"WUPC 2012"},{"start_epoch_second":1511664600,"rate_change":"×","id":"cf17-tournament-round3-open","duration_second":2400,"title":"CODE FESTIVAL 2017 Elimination Tournament Round 3 (Parallel)"},{"start_epoch_second":1479640500,"rate_change":"×","id":"s8pc-3","duration_second":10800,"title":"square869120Contest #3"},{"start_epoch_second":1506214800,"rate_change":"×","id":"jag2017summer-day3","duration_second":18000,"title":"Japan Alumni Group Summer Camp 2017 Day 3"},{"start_epoch_second":1199113200,"rate_change":"×","id":"joi2008ho","duration_second":0,"title":"第７回日本情報オリンピック 本選（オンライン）"},{"start_epoch_second":1401537600,"rate_change":"All","id":"arc024","duration_second":5400,"title":"AtCoder Regular Contest 024"},{"start_epoch_second":1360459800,"rate_change":"×","id":"joi2013ho","duration_second":14400,"title":"第１２回日本情報オリンピック 本選（オンライン）"},{"start_epoch_second":1489210500,"rate_change":"×","id":"bcu30","duration_second":7200,"title":"Battle Conference U30 - Programming Battle"},{"start_epoch_second":1379739600,"rate_change":"All","id":"jag2013summer-day2","duration_second":10800,"title":"Japan Alumni Group Summer Camp 2013 Day 2"},{"start_epoch_second":1460289600,"rate_change":"All","id":"atc002","duration_second":5400,"title":"AtCoder Typical Contest 002"},{"start_epoch_second":1136041200,"rate_change":"×","id":"joi2006yo","duration_second":0,"title":"第５回日本情報オリンピック 予選（オンライン）"},{"start_epoch_second":1366516800,"rate_change":"All","id":"JAG2013Spring","duration_second":18000,"title":"Japan Alumni Group Spring Contest 2013"},{"start_epoch_second":1482584400,"rate_change":"×","id":"xmascon16midnight","duration_second":14400,"title":"Xmas Contest 2016 深夜の部"},{"start_epoch_second":1463227200,"rate_change":"All","id":"arc053","duration_second":5400,"title":"AtCoder Regular Contest 053"},{"start_epoch_second":1439640000,"rate_change":"All","id":"arc043","duration_second":5400,"title":"AtCoder Regular Contest 043"},{"start_epoch_second":1430568000,"rate_change":"All","id":"arc038","duration_second":5400,"title":"AtCoder Regular Contest 038"},{"start_epoch_second":1425729600,"rate_change":"All","id":"arc035","duration_second":5400,"title":"AtCoder Regular Contest 035"},{"start_epoch_second":1199113200,"rate_change":"×","id":"joisc2008","duration_second":0,"title":"2008年 日本情報オリンピック春合宿OJ"},{"start_epoch_second":1354420800,"rate_change":"All","id":"utpc2012","duration_second":18000,"title":"東京大学プログラミングコンテスト2012"},{"start_epoch_second":1462622400,"rate_change":"All","id":"abc037","duration_second":7200,"title":"AtCoder Beginner Contest 037"},{"start_epoch_second":1415443200,"rate_change":"All","id":"code-festival-2014-exhibition","duration_second":3600,"title":"CODE FESTIVAL 2014 エキシビション"},{"start_epoch_second":1385895600,"rate_change":"All","id":"Recruit-Programing-contest-practice","duration_second":7200,"title":"Recruit Programming Contest 模擬練習会"},{"start_epoch_second":1497787200,"rate_change":"All","id":"agc016","duration_second":6600,"title":"AtCoder Grand Contest 016"},{"start_epoch_second":1396094400,"rate_change":"All","id":"arc020","duration_second":5400,"title":"AtCoder Regular Contest 020"},{"start_epoch_second":1418472000,"rate_change":"All","id":"arc031","duration_second":5400,"title":"AtCoder Regular Contest 031"},{"start_epoch_second":1503230400,"rate_change":"~ 2799","id":"arc081","duration_second":6000,"title":"AtCoder Regular Contest 081"},{"start_epoch_second":1489986000,"rate_change":"×","id":"rco-contest-2017-final","duration_second":14400,"title":"RCO presents 日本橋ハーフマラソン 本戦"},{"start_epoch_second":1458388800,"rate_change":"All","id":"arc049","duration_second":5400,"title":"AtCoder Regular Contest 049"},{"start_epoch_second":1500120000,"rate_change":"~ 2799","id":"arc078","duration_second":6000,"title":"AtCoder Regular Contest 078"},{"start_epoch_second":1347894000,"rate_change":"All","id":"joiopen2012c","duration_second":18000,"title":"JOI Open Contest 2012 C"},{"start_epoch_second":1485086400,"rate_change":"All","id":"agc009","duration_second":7200,"title":"AtCoder Grand Contest 009"},{"start_epoch_second":1338008400,"rate_change":"All","id":"fuka5","duration_second":10800,"title":"ふか杯 5th Contest"},{"start_epoch_second":1484980200,"rate_change":"All","id":"jrex2017","duration_second":7200,"title":"Japan Russia Exchange Programming Contest 2017"},{"start_epoch_second":1487476800,"rate_change":"×","id":"chokudai003","duration_second":28800,"title":"Chokudai Contest 003"},{"start_epoch_second":1409223600,"rate_change":"All","id":"code-formula-2014-qualb","duration_second":7200,"title":"Code Formula 2014 予選B"},{"start_epoch_second":1423900800,"rate_change":"All","id":"dwango2015-honsen","duration_second":3600,"title":"dwangoプログラミングコンテスト"},{"start_epoch_second":1474718400,"rate_change":"All","id":"code-festival-2016-quala","duration_second":7200,"title":"CODE FESTIVAL 2016 qual A"},{"start_epoch_second":1415491200,"rate_change":"All","id":"code-festival-2014-morning-easy","duration_second":5400,"title":"CODE FESTIVAL 2014 Easy"},{"start_epoch_second":1511064000,"rate_change":"×","id":"jag2017autumn","duration_second":18000,"title":"JAG Practice Contest for ACM-ICPC Asia Regional 2017"},{"start_epoch_second":1406980800,"rate_change":"All","id":"arc027","duration_second":5400,"title":"AtCoder Regular Contest 027"},{"start_epoch_second":1383566400,"rate_change":"All","id":"arc016","duration_second":5400,"title":"AtCoder Regular Contest 016"},{"start_epoch_second":1473483600,"rate_change":"×","id":"tenka1-2016-final-open","duration_second":9000,"title":"天下一プログラマーコンテスト2016本戦（オープンコンテスト）"},{"start_epoch_second":1475323200,"rate_change":"All","id":"agc005","duration_second":6600,"title":"AtCoder Grand Contest 005"},{"start_epoch_second":1354942800,"rate_change":"All","id":"wupc2nd","duration_second":14400,"title":"第2回早稲田大学プログラミングコンテスト"},{"start_epoch_second":1341057600,"rate_change":"All","id":"arc005","duration_second":5400,"title":"AtCoder Regular Contest 005"},{"start_epoch_second":1415415600,"rate_change":"All","id":"code-festival-2014-final","duration_second":10800,"title":"CODE FESTIVAL 2014 決勝"},{"start_epoch_second":1511606700,"rate_change":"×","id":"cf17-exhibition-open","duration_second":3600,"title":"CODE FESTIVAL 2017 Exhibition (Parallel)"},{"start_epoch_second":1347685200,"rate_change":"All","id":"tenka1-2012-final","duration_second":7200,"title":"天下一プログラマーコンテスト2012 決勝"},{"start_epoch_second":1416657600,"rate_change":"All","id":"abc015","duration_second":7200,"title":"AtCoder Beginner Contest 015"},{"start_epoch_second":1356966000,"rate_change":"×","id":"joi2013yo","duration_second":0,"title":"第１２回日本情報オリンピック 予選（オンライン）"},{"start_epoch_second":1436616000,"rate_change":"All","id":"abc026","duration_second":7200,"title":"AtCoder Beginner Contest 026"},{"start_epoch_second":1442722500,"rate_change":"All","id":"ttpc2015","duration_second":18000,"title":"東京工業大学プログラミングコンテスト2015"},{"start_epoch_second":1426334400,"rate_change":"All","id":"indeednow-quala","duration_second":7200,"title":"Indeedなう（予選A）"},{"start_epoch_second":1488024000,"rate_change":"All","id":"mujin-pc-2017","duration_second":7200,"title":"Mujin Programming Challenge 2017"},{"start_epoch_second":1305342000,"rate_change":"All","id":"utpc2011","duration_second":18000,"title":"UTPC 2011"},{"start_epoch_second":1509192000,"rate_change":"~ 1199","id":"abc076","duration_second":6000,"title":"AtCoder Beginner Contest 076"},{"start_epoch_second":1447546200,"rate_change":"All","id":"code-festival-2015-morning-middle","duration_second":5400,"title":"CODE FESTIVAL 2015 あさぷろ Middle"},{"start_epoch_second":1363521600,"rate_change":"All","id":"arc013","duration_second":5400,"title":"AtCoder Regular Contest 013"},{"start_epoch_second":1464436800,"rate_change":"All","id":"abc038","duration_second":7200,"title":"AtCoder Beginner Contest 038"},{"start_epoch_second":1429417800,"rate_change":"All","id":"jag2015spring","duration_second":18000,"title":"Japan Alumni Group Spring Contest 2015"},{"start_epoch_second":1392552000,"rate_change":"All","id":"abc004","duration_second":7200,"title":"AtCoder Beginner Contest 004"},{"start_epoch_second":1391313600,"rate_change":"All","id":"birthday0410","duration_second":18000,"title":"お誕生日コンテスト"},{"start_epoch_second":1445660400,"rate_change":"All","id":"kupc2015","duration_second":18000,"title":"京都大学プログラミングコンテスト2015"},{"start_epoch_second":1293807600,"rate_change":"×","id":"joisc2011","duration_second":0,"title":"2011年 日本情報オリンピック春合宿OJ"},{"start_epoch_second":1388502000,"rate_change":"×","id":"joi2014ho","duration_second":0,"title":"第１３回日本情報オリンピック 本選（オンライン）"},{"start_epoch_second":1450008000,"rate_change":"All","id":"arc046","duration_second":5400,"title":"AtCoder Regular Contest 046"},{"start_epoch_second":1488715200,"rate_change":"×","id":"yahoo-procon2017-qual","duration_second":7200,"title":"「みんなのプロコン」"},{"start_epoch_second":1415491200,"rate_change":"All","id":"code-festival-2014-morning-middle","duration_second":5400,"title":"CODE FESTIVAL 2014 Middle"},{"start_epoch_second":1493467200,"rate_change":"~ 1199","id":"abc060","duration_second":6000,"title":"AtCoder Beginner Contest 060"},{"start_epoch_second":1415491200,"rate_change":"All","id":"code-festival-2014-morning-hard","duration_second":5400,"title":"CODE FESTIVAL 2014 Hard"},{"start_epoch_second":1481371200,"rate_change":"~ 1199","id":"abc049","duration_second":6000,"title":"AtCoder Beginner Contest 049"},{"start_epoch_second":1340510400,"rate_change":"All","id":"ijpc2012-2","duration_second":18000,"title":"IOIer Japan Programming Contest #2"},{"start_epoch_second":1415415600,"rate_change":"All","id":"code-festival-2014-final-open","duration_second":10800,"title":"CODE FESTIVAL 2014 決勝（オープン）"},{"start_epoch_second":1452340800,"rate_change":"All","id":"abc032","duration_second":7200,"title":"AtCoder Beginner Contest 032"},{"start_epoch_second":1489838400,"rate_change":"~ 2799","id":"arc070","duration_second":6000,"title":"AtCoder Regular Contest 070"},{"start_epoch_second":1445142600,"rate_change":"All","id":"ijpc2015","duration_second":18000,"title":"IOIer Japan Programming Contest 2015"},{"start_epoch_second":1461474000,"rate_change":"All","id":"jag2016-domestic","duration_second":12600,"title":"JAG Contest 2016 Domestic"},{"start_epoch_second":1492257600,"rate_change":"All","id":"agc013","duration_second":9000,"title":"AtCoder Grand Contest 013"},{"start_epoch_second":1400932800,"rate_change":"All","id":"abc009","duration_second":7200,"title":"AtCoder Beginner Contest 009"},{"start_epoch_second":1167577200,"rate_change":"×","id":"joi2007ho","duration_second":0,"title":"第６回日本情報オリンピック 本選（オンライン）"}]